    [
        {
            "id":"1",
            "AllSrc" : 
                    [
                        {
                            "src": "https://bes0610.github.io/imPortofilo2/Main2.jpg"
                        },
                        {
                            "src": "https://bes0610.github.io/imPortofilo3/Main3.jpg"
                        },
                        {
                            "src": "https://bes0610.github.io/imPortofilo4/Main4.jpg"
                        },
                        {
                            "src": "https://bes0610.github.io/imPortofilo6/Main6.jpg"
                        }
                    ]
        }
    ]
    
